seq2seq_lstm/__init__.py
seq2seq_lstm/seq2seq_lstm.py
seq2seq_lstm-0.1.5.dist-info/LICENSE
seq2seq_lstm-0.1.5.dist-info/METADATA
seq2seq_lstm-0.1.5.dist-info/WHEEL
seq2seq_lstm-0.1.5.dist-info/top_level.txt
seq2seq_lstm-0.1.5.dist-info/RECORD
