Metadata-Version: 2.1
Name: seq2seq-lstm
Version: 0.1.5
Summary: Sequence-to-sequence classifier based on LSTM with the simple sklearn-like interface
Home-page: https://github.com/bond005/seq2seq
Author: Ivan Bondarenko
Author-email: bond005@yandex.ru
License: Apache License Version 2.0
Keywords: seq2seq,sequence-to-sequence,lstm,nlp,keras,scikit-learn
Platform: UNKNOWN
Classifier: Development Status :: 3 - Alpha
Classifier: Intended Audience :: Science/Research
Classifier: Intended Audience :: Developers
Classifier: Topic :: Software Development
Classifier: Topic :: Scientific/Engineering
Classifier: Topic :: Scientific/Engineering :: Artificial Intelligence
Classifier: Topic :: Text Processing
Classifier: Topic :: Text Processing :: Linguistic
Classifier: License :: OSI Approved :: Apache Software License
Classifier: Programming Language :: Python :: 2.6
Classifier: Programming Language :: Python :: 2.7
Classifier: Programming Language :: Python :: 3.4
Classifier: Programming Language :: Python :: 3.5
Classifier: Programming Language :: Python :: 3.6
Requires-Dist: h5py (>=2.10.0)
Requires-Dist: tensorflow (>=2.2.1)
Requires-Dist: numpy (>=1.18.5)
Requires-Dist: scikit-learn (>=0.23.2)
